module/counter.v
module counter (
    input clk,
    input rst,
    output  reg [4:0] result
);
    

    always @(posedge clk or posedge rst) begin
        if (rst) begin
            result <= 5'b0;
        end else begin
            result <= result + 1;
        end
        
    end
endmodule

waveform.vcd
$version Generated by VerilatedVcd $end
$date Mon Oct 20 09:37:17 2025
 $end
$timescale   1ps $end

 $scope module TOP $end
  $var wire  1 # clk $end
  $var wire  5 % result [4:0] $end
  $var wire  1 $ rst $end
  $scope module counter $end
   $var wire  1 # clk $end
   $var wire  5 % result [4:0] $end
   $var wire  1 $ rst $end
  $upscope $end
 $upscope $end
$enddefinitions $end


#5
0#
0$
b00000 %
#10
1#
1$
#15
0#
#20
1#
#25
0#
#30
1#
0$
b00001 %
#35
0#
#40
1#
b00010 %
#45
0#
#50
1#
b00011 %
#55
0#
#60
1#
b00100 %
#65
0#
#70
1#
b00101 %
#75
0#
#80
1#
b00110 %
#85
0#
#90
1#
b00111 %
#95
0#
#100
1#
b01000 %
#105
0#
#110
1#
b01001 %
#115
0#
#120
1#
b01010 %
#125
0#
#130
1#
b01011 %
#135
0#
#140
1#
b01100 %
#145
0#
#150
1#
b01101 %
#155
0#
#160
1#
b01110 %
#165
0#
#170
1#
b01111 %
#175
0#
#180
1#
b10000 %
#185
0#
#190
1#
b10001 %
#195
0#
#200
1#
b10010 %
#205
0#
#210
1#
b10011 %
#215
0#
#220
1#
b10100 %
#225
0#
#230
1#
b10101 %
#235
0#
#240
1#
b10110 %
#245
0#
#250
1#
b10111 %
#255
0#
#260
1#
b11000 %
#265
0#
#270
1#
b11001 %
#275
0#
#280
1#
b11010 %
#285
0#
#290
1#
b11011 %
#295
0#
#300
1#
b11100 %
#305
0#
#310
1#
b11101 %
#315
0#
#320
1#
b11110 %
#325
0#
#330
1#
b11111 %
#335
0#
#340
1#
b00000 %
#345
0#
#350
1#
b00001 %
#355
0#
#360
1#
b00010 %
#365
0#
#370
1#
b00011 %
#375
0#
#380
1#
b00100 %
#385
0#
#390
1#
b00101 %
#395
0#
#400
1#
b00110 %
#405
0#
#410
1#
b00111 %
#415
0#
#420
1#
b01000 %
#425
0#
#430
1#
b01001 %
#435
0#
#440
1#
b01010 %
#445
0#
#450
1#
b01011 %
#455
0#
#460
1#
b01100 %
#465
0#
#470
1#
b01101 %
#475
0#
#480
1#
b01110 %
#485
0#
#490
1#
b01111 %
#495
0#
#500
1#
b10000 %
#505
0#
#510
1#
b10001 %
#515
0#
#520
1#
b10010 %
#525
0#
#530
1#
b10011 %
#535
0#
#540
1#
b10100 %
#545
0#
#550
1#
b10101 %
#555
0#
#560
1#
b10110 %
#565
0#
#570
1#
b10111 %
#575
0#
#580
1#
b11000 %
#585
0#
#590
1#
b11001 %
#595
0#
#600
1#
b11010 %
#605
0#
#610
1#
b11011 %
#615
0#
#620
1#
b11100 %
#625
0#
#630
1#
b11101 %
#635
0#
#640
1#
b11110 %
#645
0#
#650
1#
b11111 %
#655
0#
#660
1#
b00000 %
#665
0#
#670
1#
b00001 %
#675
0#
#680
1#
b00010 %
#685
0#
#690
1#
b00011 %
#695
0#
#700
1#
b00100 %
#705
0#
#710
1#
b00101 %
#715
0#
#720
1#
b00110 %
#725
0#
#730
1#
b00111 %
#735
0#
#740
1#
b01000 %
#745
0#
#750
1#
b01001 %
#755
0#
#760
1#
b01010 %
#765
0#
#770
1#
b01011 %
#775
0#
#780
1#
b01100 %
#785
0#
#790
1#
b01101 %
#795
0#
#800
1#
b01110 %
#805
0#
#810
1#
b01111 %
#815
0#
#820
1#
b10000 %
#825
0#
#830
1#
b10001 %
#835
0#
#840
1#
b10010 %
#845
0#
#850
1#
b10011 %
#855
0#
#860
1#
b10100 %
#865
0#
#870
1#
b10101 %
#875
0#
#880
1#
b10110 %
#885
0#
#890
1#
b10111 %
#895
0#
#900
1#
b11000 %
#905
0#
#910
1#
b11001 %
#915
0#
#920
1#
b11010 %
#925
0#
#930
1#
b11011 %
#935
0#
#940
1#
b11100 %
#945
0#
#950
1#
b11101 %
#955
0#
#960
1#
b11110 %
#965
0#
#970
1#
b11111 %
#975
0#
#980
1#
b00000 %
#985
0#
#990
1#
b00001 %
#995
0#
#1000
1#
b00010 %
#1005
0#
#1010
1#
b00011 %
#1015
0#
#1020
1#
b00100 %
#1025
0#
#1030
1#
b00101 %
#1035
0#
#1040
1#
b00110 %
#1045
0#
#1050
1#
b00111 %
#1055
0#
#1060
1#
b01000 %
#1065
0#
#1070
1#
b01001 %
#1075
0#
#1080
1#
b01010 %
#1085
0#
#1090
1#
b01011 %
#1095
0#
#1100
1#
b01100 %
#1105
0#
#1110
1#
b01101 %
#1115
0#
#1120
1#
b01110 %
#1125
0#
#1130
1#
b01111 %
#1135
0#
#1140
1#
b10000 %
#1145
0#
#1150
1#
b10001 %
#1155
0#
#1160
1#
b10010 %
#1165
0#
#1170
1#
b10011 %
#1175
0#
#1180
1#
b10100 %
#1185
0#
#1190
1#
b10101 %
#1195
0#
#1200
1#
b10110 %
#1205
0#
#1210
1#
b10111 %
#1215
0#
#1220
1#
b11000 %
#1225
0#
#1230
1#
b11001 %
#1235
0#
#1240
1#
b11010 %
#1245
0#
#1250
1#
b11011 %
#1255
0#
#1260
1#
b11100 %
#1265
0#
#1270
1#
b11101 %
#1275
0#
#1280
1#
b11110 %
#1285
0#
#1290
1#
b11111 %
#1295
0#
#1300
1#
b00000 %
#1305
0#
#1310
1#
b00001 %
#1315
0#
#1320
1#
b00010 %
#1325
0#
#1330
1#
b00011 %
#1335
0#
#1340
1#
b00100 %
#1345
0#
#1350
1#
b00101 %
#1355
0#
#1360
1#
b00110 %
#1365
0#
#1370
1#
b00111 %
#1375
0#
#1380
1#
b01000 %
#1385
0#
#1390
1#
b01001 %
#1395
0#
#1400
1#
b01010 %
#1405
0#
#1410
1#
b01011 %
#1415
0#
#1420
1#
b01100 %
#1425
0#
#1430
1#
b01101 %
#1435
0#
#1440
1#
b01110 %
#1445
0#
#1450
1#
b01111 %
#1455
0#
#1460
1#
b10000 %
#1465
0#
#1470
1#
b10001 %
#1475
0#
#1480
1#
b10010 %
#1485
0#
#1490
1#
b10011 %
#1495
0#
#1500
1#
b10100 %
#1505
0#
#1510
1#
b10101 %
#1515
0#
#1520
1#
b10110 %
#1525
0#
#1530
1#
b10111 %
#1535
0#
#1540
1#
b11000 %
#1545
0#
#1550
1#
b11001 %
#1555
0#
#1560
1#
b11010 %
#1565
0#
#1570
1#
b11011 %
#1575
0#
#1580
1#
b11100 %
#1585
0#
#1590
1#
b11101 %
#1595
0#
#1600
1#
b11110 %
#1605
0#
#1610
1#
b11111 %
#1615
0#
#1620
1#
b00000 %
#1625
0#
#1630
1#
b00001 %
#1635
0#
#1640
1#
b00010 %
#1645
0#
#1650
1#
b00011 %
#1655
0#
#1660
1#
b00100 %
#1665
0#
#1670
1#
b00101 %
#1675
0#
#1680
1#
b00110 %
#1685
0#
#1690
1#
b00111 %
#1695
0#
#1700
1#
b01000 %
#1705
0#
#1710
1#
b01001 %
#1715
0#
#1720
1#
b01010 %
#1725
0#
#1730
1#
b01011 %
#1735
0#
#1740
1#
b01100 %
#1745
0#
#1750
1#
b01101 %
#1755
0#
#1760
1#
b01110 %
#1765
0#
#1770
1#
b01111 %
#1775
0#
#1780
1#
b10000 %
#1785
0#
#1790
1#
b10001 %
#1795
0#
#1800
1#
b10010 %
#1805
0#
#1810
1#
b10011 %
#1815
0#
#1820
1#
b10100 %
#1825
0#
#1830
1#
b10101 %
#1835
0#
#1840
1#
b10110 %
#1845
0#
#1850
1#
b10111 %
#1855
0#
#1860
1#
b11000 %
#1865
0#
#1870
1#
b11001 %
#1875
0#
#1880
1#
b11010 %
#1885
0#
#1890
1#
b11011 %
#1895
0#
#1900
1#
b11100 %
#1905
0#
#1910
1#
b11101 %
#1915
0#
#1920
1#
b11110 %
#1925
0#
#1930
1#
b11111 %
#1935
0#
#1940
1#
b00000 %
#1945
0#
#1950
1#
b00001 %
#1955
0#
#1960
1#
b00010 %
#1965
0#
#1970
1#
b00011 %
#1975
0#
#1980
1#
b00100 %
#1985
0#
#1990
1#
b00101 %
#1995
0#
#2000
1#
b00110 %
